Metadata-Version: 1.1
Name: sqlemon
Version: 0.8.4
Summary: Manage sqlalchemy connections to Google Cloud SQL
Home-page: https://github.com/DanielSank/sqlemon
Author: Daniel Sank
Author-email: sank.daniel@gmail.com
License: MIT
Download-URL: https://github.com/DanielSank/sqlemon/tarball/0.8.4
Keywords: sql
Platform: UNKNOWN
